odoo/addons/partner_route/README.rst
odoo/addons/partner_route/__init__.py
odoo/addons/partner_route/__manifest__.py
odoo/addons/partner_route/i18n/eu_ES.po
odoo/addons/partner_route/i18n/partner_route.pot
odoo/addons/partner_route/models/__init__.py
odoo/addons/partner_route/models/partner_route.py
odoo/addons/partner_route/models/res_partner.py
odoo/addons/partner_route/readme/CONTRIBUTORS.rst
odoo/addons/partner_route/readme/DESCRIPTION.rst
odoo/addons/partner_route/readme/USAGE.rst
odoo/addons/partner_route/security/ir.model.access.csv
odoo/addons/partner_route/security/res_groups.xml
odoo/addons/partner_route/static/description/icon.png
odoo/addons/partner_route/static/description/index.html
odoo/addons/partner_route/views/partner_route_view.xml
odoo12_addon_partner_route-12.0.1.0.0.99.dev7.dist-info/METADATA
odoo12_addon_partner_route-12.0.1.0.0.99.dev7.dist-info/WHEEL
odoo12_addon_partner_route-12.0.1.0.0.99.dev7.dist-info/top_level.txt
odoo12_addon_partner_route-12.0.1.0.0.99.dev7.dist-info/RECORD
